ALU_32bit.v
module ALU_32bit(A,B,ALU_Sel,ALU_Out,Carryout);
    input [31:0] A;
    input [31:0] B;
    input [3:0] ALU_Sel;
    output reg [31:0] ALU_Out;
    output reg Carryout;


always @(*) begin
    case (ALU_Sel)
        4'b0000: begin // Addition
            {Carryout, ALU_Out} = A + B;
        end
        4'b0001: begin // Subtraction
            {Carryout, ALU_Out} = A - B;
        end
        4'b0010: begin // Multiplication
            ALU_Out = A * B;
            Carryout = 1'b0; // Carryout is not relevant for multiplication
        end
        4'b0011: begin // Division
            ALU_Out = A / B;
            Carryout = 1'b0; // Carryout is not relevant for division
        end
        4'b0100: begin // Logical shift left
            ALU_Out = A << 1;
            Carryout = 1'b0; // Carryout is not relevant for shift operations
        end
        4'b0101: begin // Logical shift right
            ALU_Out = A >> 1;
            Carryout = 1'b0; // Carryout is not relevant for shift operations
        end
        4'b0110: begin // Rotate left
            ALU_Out = {A[30:0], A[31]};
            Carryout = 1'b0; // Carryout is not relevant for rotate operations
        end
        4'b0111: begin // Rotate right
            ALU_Out = {A[0], A[31:1]};
            Carryout = 1'b0; // Carryout is not relevant for rotate operations
        end
        4'b1000: begin // Logical AND
            ALU_Out = A & B;
            Carryout = 1'b0; // Carryout is not relevant for logical operations
        end
        4'b1001: begin // Logical OR
            ALU_Out = A | B;
            Carryout = 1'b0; // Carryout is not relevant for logical operations
        end
        4'b1010: begin // Logical XOR
            ALU_Out = A ^ B;
            Carryout = 1'b0; // Carryout is not relevant for logical operations
        end
        4'b1011: begin // Logical NOR
            ALU_Out = ~(A | B);
            Carryout = 1'b0; // Carryout is not relevant for logical operations
        end
        4'b1100: begin // Logical NAND
            ALU_Out = ~(A & B);
            Carryout = 1'b0; // Carryout is not relevant for logical operations
        end
        4'b1101: begin // Logical XNOR
            ALU_Out = ~(A ^ B);
            Carryout = 1'b0; // Carryout is not relevant for logical operations
        end
        4'b1110: begin // Greater comparison
            ALU_Out = (A > B) ? 32'd1 : 32'd0;
            Carryout = 1'b0; // Carryout is not relevant for comparison operations
        end
        4'b1111: begin // Equal comparison
            ALU_Out = (A == B) ? 32'd1 : 32'd0;
            Carryout = 1'b0; // Carryout is not relevant for comparison operations
        end
        default: begin
            ALU_Out = 32'b0;
            Carryout = 1'b0;
        end
    endcase
end

endmodule

Testbench_32bit_ALU.v
`timescale 1ns/1ps
`include "ALU_32bit.v"

module Testbench_32bit_ALU;
    reg [31:0] A, B;
    reg [3:0] ALU_Sel;
    wire [31:0] ALU_Out;
    wire Carryout;

    ALU_32bit DUT (
        .A(A),
        .B(B),
        .ALU_Sel(ALU_Sel),
        .ALU_Out(ALU_Out),
        .Carryout(Carryout)
    );

    initial begin
        $dumpfile("alu.vcd");
        $dumpvars(0, Testbench_32bit_ALU);

        // Test Addition
        A = 32'h12345678;
        B = 32'h87654321;
        ALU_Sel = 4'b0000;
        #10;

        // Test Subtraction
        A = 32'h12345678;
        B = 32'h87654321;
        ALU_Sel = 4'b0001;
        #10;

        // Test Multiplication
        A = 32'h00000012;
        B = 32'h00000034;
        ALU_Sel = 4'b0010;
        #10;

        // Test Division
        A = 32'h00000078;
        B = 32'h00000012;
        ALU_Sel = 4'b0011;
        #10;

        // Test Logical Shift Left
        A = 32'h12345678;
        B = 32'h00000000;
        ALU_Sel = 4'b0100;
        #10;

        // Test Logical Shift Right
        A = 32'h12345678;
        B = 32'h00000000;
        ALU_Sel = 4'b0101;
        #10;

        // Test Rotate Left
        A = 32'h12345678;
        B = 32'h00000000;
        ALU_Sel = 4'b0110;
        #10;

        // Test Rotate Right
        A = 32'h12345678;
        B = 32'h00000000;
        ALU_Sel = 4'b0111;
        #10;

        // Test Logical AND
        A = 32'h12345678;
        B = 32'h87654321;
        ALU_Sel = 4'b1000;
        #10;

        // Test Logical OR
        A = 32'h12345678;
        B = 32'h87654321;
        ALU_Sel = 4'b1001;
        #10;

        // Test Logical XOR
        A = 32'h12345678;
        B = 32'h87654321;
        ALU_Sel = 4'b1010;
        #10;

        // Test Logical NOR
        A = 32'h12345678;
        B = 32'h87654321;
        ALU_Sel = 4'b1011;
        #10;

        // Test Logical NAND
        A = 32'h12345678;
        B = 32'h87654321;
        ALU_Sel = 4'b1100;
        #10;

        // Test Logical XNOR
        A = 32'h12345678;
        B = 32'h87654321;
        ALU_Sel = 4'b1101;
        #10;

        // Test Greater Comparison
        A = 32'h12345678;
        B = 32'h87654321;
        ALU_Sel = 4'b1110;
        #10;

        // Test Equal Comparison
        A = 32'h12345678;
        B = 32'h12345678;
        ALU_Sel = 4'b1111;
        #10;

        $finish;
    end
endmodule

alu.vcd
$date
	Fri Apr 12 00:54:37 2024
$end
$version
	Icarus Verilog
$end
$timescale
	1ps
$end
$scope module Testbench_32bit_ALU $end
$var wire 32 ! ALU_Out [31:0] $end
$var wire 1 " Carryout $end
$var reg 32 # A [31:0] $end
$var reg 4 $ ALU_Sel [3:0] $end
$var reg 32 % B [31:0] $end
$scope module DUT $end
$var wire 32 & A [31:0] $end
$var wire 4 ' ALU_Sel [3:0] $end
$var wire 32 ( B [31:0] $end
$var reg 32 ) ALU_Out [31:0] $end
$var reg 1 * Carryout $end
$upscope $end
$upscope $end
$enddefinitions $end
#0
$dumpvars
0*
b10011001100110011001100110011001 )
b10000111011001010100001100100001 (
b0 '
b10010001101000101011001111000 &
b10000111011001010100001100100001 %
b0 $
b10010001101000101011001111000 #
0"
b10011001100110011001100110011001 !
$end
#10000
1*
1"
b10001010110011110001001101010111 )
b10001010110011110001001101010111 !
b1 $
b1 '
#20000
0*
0"
b1110101000 )
b1110101000 !
b10 $
b10 '
b110100 %
b110100 (
b10010 #
b10010 &
#30000
b110 )
b110 !
b11 $
b11 '
b10010 %
b10010 (
b1111000 #
b1111000 &
#40000
b100100011010001010110011110000 )
b100100011010001010110011110000 !
b100 $
b100 '
b0 %
b0 (
b10010001101000101011001111000 #
b10010001101000101011001111000 &
#50000
b1001000110100010101100111100 )
b1001000110100010101100111100 !
b101 $
b101 '
#60000
b100100011010001010110011110000 )
b100100011010001010110011110000 !
b110 $
b110 '
#70000
b1001000110100010101100111100 )
b1001000110100010101100111100 !
b111 $
b111 '
#80000
b10001001000100001000100000 )
b10001001000100001000100000 !
b1000 $
b1000 '
b10000111011001010100001100100001 %
b10000111011001010100001100100001 (
#90000
b10010111011101010101011101111001 )
b10010111011101010101011101111001 !
b1001 $
b1001 '
#100000
b10010101010100010001010101011001 )
b10010101010100010001010101011001 !
b1010 $
b1010 '
#110000
b1101000100010101010100010000110 )
b1101000100010101010100010000110 !
b1011 $
b1011 '
#120000
b11111101110110111011110111011111 )
b11111101110110111011110111011111 !
b1100 $
b1100 '
#130000
b1101010101011101110101010100110 )
b1101010101011101110101010100110 !
b1101 $
b1101 '
#140000
b0 )
b0 !
b1110 $
b1110 '
#150000
b1 )
b1 !
b1111 $
b1111 '
b10010001101000101011001111000 %
b10010001101000101011001111000 (
