sample_circuit.v
module sample_circuit(A,B,C,D,E,Y);

input A,B,C,D,E;
output Y;
wire W1,W2,W3,W4;

or o1(W1,A,B);
and a1(W2,C,D);
not n1(W3,W1);
or o2(W4,W2,W3);
and a2(Y,W4,E);

endmodule

sample_circuit_tb.v
`include "sample_circuit.v"

module sample_circuit_tb;
    // Inputs
    reg A, B, C, D, E;

    // Outputs
    wire Y;

    // Instantiate the Unit Under Test (UUT)
    sample_circuit uut (
        .A(A),
        .B(B),
        .C(C),
        .D(D),
        .E(E),
        .Y(Y)
    );

    initial begin
        $dumpfile("sample_circuit.vcd");
        $dumpvars(0,sample_circuit_tb);

        A = 0;
        B = 0;
        C = 0;
        D = 0;
        E = 0;

        // Wait 100 ns for global reset to finish
        #100;


        A = 0; B = 0; C = 0; D = 0; E = 1;
        #100;

        A = 0; B = 0; C = 0; D = 1; E = 0;
        #100;

        A = 0; B = 0; C = 1; D = 0; E = 1;
        #100;

        A = 0; B = 1; C = 0; D = 1; E = 0;
        #100;

        A = 1; B = 0; C = 1; D = 0; E = 1;
        #100;

        A = 1; B = 1; C = 0; D = 0; E = 0;
        #100;

        A = 1; B = 0; C = 0; D = 1; E = 1;
        #100;

        A = 0; B = 1; C = 1; D = 1; E = 1;
        #100;

        $finish;
    end
endmodule

sample_circuit.vcd
$date
	Thu Apr 11 21:47:18 2024
$end
$version
	Icarus Verilog
$end
$timescale
	1s
$end






$scope module sample_circuit_tb $end
$var wire 1 ! Y $end
$var reg 1 " A $end
$var reg 1 # B $end
$var reg 1 $ C $end
$var reg 1 % D $end
$var reg 1 & E $end
$scope module uut $end
$var wire 1 ' A $end
$var wire 1 ( B $end
$var wire 1 ) C $end
$var wire 1 * D $end
$var wire 1 + E $end
$var wire 1 , W1 $end
$var wire 1 - W2 $end
$var wire 1 . W3 $end
$var wire 1 / W4 $end
$var wire 1 ! Y $end
$upscope $end
$upscope $end
$enddefinitions $end
#0
$dumpvars
1/
1.
0-
0,
0+
0*
0)
0(
0'
0&
0%
0$
0#
0"
0!
$end
#100
1!
1&
1+
#200
0!
0&
0+
1%
1*
#300
1!
1&
1+
0%
0*
1$
1)
#400
0/
0.
0!
1,
0&
0+
1%
1*
0$
0)
1#
1(
#500
1&
1+
0%
0*
1$
1)
0#
0(
1"
1'
#600
0&
0+
0$
0)
1#
1(
#700
1&
1+
1%
1*
0#
0(
#800
1!
1/
1-
1$
1)
1#
1(
0"
0'
